<?xml version="1.0"?><api><continue rvcontinue="20061031193910|84891363" continue="||" /><warnings><main xml:space="preserve">Subscribe to the mediawiki-api-announce mailing list at &lt;https://lists.wikimedia.org/postorius/lists/mediawiki-api-announce.lists.wikimedia.org/&gt; for notice of API deprecations and breaking changes. Use [[Special:ApiFeatureUsage]] to see usage of deprecated features by your application.</main><revisions xml:space="preserve">Because "rvslots" was not specified, a legacy format has been used for the output. This format is deprecated, and in the future the new format will always be used.</revisions></warnings><query><pages><page _idx="1913571" pageid="1913571" ns="0" title="Gay literature"><revisions><rev timestamp="2006-11-06T19:58:18Z" contentformat="text/x-wiki" contentmodel="wikitext" xml:space="preserve">'''LGBT''' or '''Lesbian, Gay, Bisexual and Transgender Literature''' is an all encompassing term for [[literature]] produced by people who are [[Lesbian]], [[Gay]], [[Bisexual]] or [[Transgender]] or involving [[fictional character|characters]], [[plot]] lines or themes concerning this community. 

==Late 19th Century==
*[[Aestheticism]]
*[[Charles Baudelaire]]
*[[Emily Dickinson]]
*[[Théophile Gautier]]
*[[Henry James]]
*[[Walter Pater]]
*[[Marcel Proust]]
*[[Arthur Rimbaud]]
*[[Algernon Swinburne]]
*[[Walt Whitman]]
*[[Oscar Wilde]]

==Twentieth century==
===Pre-Stonewall===
*[[E.M. Forster]]
*[[Jean Cocteau]]
*[[Marguerite Yourcenar]]
*[[D.H. Lawrence]]
*[[Djuna Barnes]]
*[[William Carlos Williams]]
*[[Christopher Isherwood]]
*[[W.H. Auden]]
*[[W. Somerset Maugham]]
*[[Jean Genet]]
*[[Frank O'Hara]]
*[[Joe Orton]]
*[[William S. Burroughs]]
*[[Allen Ginsberg]]
*[[James Baldwin (writer)|James Baldwin]]
*[[Radclyffe Hall]] and [[The Well of Loneliness]]
*[[Noel Coward]]
*[[Avery Hopwood]] - [[United States|American]] [[playwright]].
*[[Gertrude Stein]] and [[Alice B. Toklas]]
*[[Mae West]]
*[[Colette]]
*[[Tennessee Williams]]
*[[Evelyn Waugh]]
*[[Magnus Hirschfeld]]
*[[Langston Hughes]]
*[[J.R. Ackerley]]
*[[Reinaldo Arenas]]
*[[Virginia Woolf]]
*[[Truman Capote]]
*[[Constantine P. Cavafy]]

===Post-Stonewall===
*[[Andrew Tobias]] and [[The Best Little Boy in the World]].
*[[Rita Mae Brown]] and [[Rubyfruit Jungle]].
*[[Edward Albee]]
*[[Gore Vidal]]
*[[Terrence McNally]]
*[[Tony Kushner]]
*[[Armistead Maupin]]
*[[Paula Vogel]]
*[[Christopher Rice]]
*[[Edmund White]]
*[[Randy Shilts]]
*[[Larry Kramer]]
*[[Alice Walker]]
*[[Colm Toibin]]
*[[Shyam Selvadurai]]
*[[Gudmund Vindland]]
*[[Timothy Findley]]
*[[Gregory Maguire]]
*[[Keith Ridgway]]
*[[Pål Johan Karlsen]]
*[[Douglas Coupland]]
*[[Henry Alley]]
*[[James Robert Baker]]
*[[Michel Tremblay]]
*[[Roland Michel Tremblay]]

==See also==
*[[Lambda Literary Award]]
*[[Singapore gay literature]]
*[[Marguerite Yourcenar]]

==External links==
*[http://www.glbtq.com/subject/literature_a-b.html Encyclopedia of Gay, Lesbian, Bisexual, Transgender and Queer Culture on Gay Literature]
*[http://www.lodestarquarterly.com Lodestar Quarterly — an Online Journal of the Finest Gay, Lesbian, and Queer Literature]

[[Category:LGBT history]]
[[Category:LGBT literature|*]]

{{LGBT-stub}}

[[pl:Literatura gejowska i lesbijska]]</rev></revisions></page></pages></query></api>