<?xml version="1.0"?><api><continue rvcontinue="20070928214341|160999716" continue="||" /><warnings><main xml:space="preserve">Subscribe to the mediawiki-api-announce mailing list at &lt;https://lists.wikimedia.org/postorius/lists/mediawiki-api-announce.lists.wikimedia.org/&gt; for notice of API deprecations and breaking changes. Use [[Special:ApiFeatureUsage]] to see usage of deprecated features by your application.</main><revisions xml:space="preserve">Because "rvslots" was not specified, a legacy format has been used for the output. This format is deprecated, and in the future the new format will always be used.</revisions></warnings><query><pages><page _idx="852252" pageid="852252" ns="0" title="Untouchability"><revisions><rev timestamp="2007-09-28T21:53:47Z" contentformat="text/x-wiki" contentmodel="wikitext" xml:space="preserve">#redirect [[Untouchable]]</rev></revisions></page></pages></query></api>